jupyterlab_pachyderm/__init__.py
jupyterlab_pachyderm/_version.py
jupyterlab_pachyderm/dev_server.py
jupyterlab_pachyderm/env.py
jupyterlab_pachyderm/handlers.py
jupyterlab_pachyderm/log.py
jupyterlab_pachyderm/pfs_manager.py
jupyterlab_pachyderm/pps_client.py
jupyterlab_pachyderm/labextension/package.json
jupyterlab_pachyderm/labextension/schemas/jupyterlab-pachyderm/examples.json
jupyterlab_pachyderm/labextension/schemas/jupyterlab-pachyderm/help.json
jupyterlab_pachyderm/labextension/schemas/jupyterlab-pachyderm/mount.json
jupyterlab_pachyderm/labextension/schemas/jupyterlab-pachyderm/package.json.orig
jupyterlab_pachyderm/labextension/schemas/jupyterlab-pachyderm/telemetry.json
jupyterlab_pachyderm/labextension/static/197.4be637ba68f12200884d.js
jupyterlab_pachyderm/labextension/static/202.2d27d0c82035d8e46c16.js
jupyterlab_pachyderm/labextension/static/336.f296352f98b7dbcf78f7.js
jupyterlab_pachyderm/labextension/static/336.f296352f98b7dbcf78f7.js.LICENSE.txt
jupyterlab_pachyderm/labextension/static/357.062959dcd2fab3cea88b.js
jupyterlab_pachyderm/labextension/static/357.062959dcd2fab3cea88b.js.LICENSE.txt
jupyterlab_pachyderm/labextension/static/543.79ced51388dd3ea18595.js
jupyterlab_pachyderm/labextension/static/543.79ced51388dd3ea18595.js.LICENSE.txt
jupyterlab_pachyderm/labextension/static/728.ba90058ad38561d0e60b.js
jupyterlab_pachyderm/labextension/static/842.7031191212721bc4c0b4.js
jupyterlab_pachyderm/labextension/static/remoteEntry.8618a4e0d4a801d516a7.js
jupyterlab_pachyderm/labextension/static/style.js
jupyterlab_pachyderm/labextension/static/third-party-licenses.json
jupyterlab_pachyderm/tests/__init__.py
jupyterlab_pachyderm/tests/conftest.py
jupyterlab_pachyderm/tests/setup_large_repo.py
jupyterlab_pachyderm/tests/test_config.py
jupyterlab_pachyderm/tests/test_integrations.py
jupyterlab_pachyderm/tests/test_pps.py
jupyterlab_pachyderm/tests/data/TestNotebook.ipynb
jupyterlab_pachyderm/tests/data/requirements.txt
jupyterlab_pachyderm-2.12.2.dist-info/LICENSE
jupyterlab_pachyderm-2.12.2.dist-info/METADATA
jupyterlab_pachyderm-2.12.2.dist-info/WHEEL
jupyterlab_pachyderm-2.12.2.dist-info/top_level.txt
jupyterlab_pachyderm-2.12.2.dist-info/RECORD
