Metadata-Version: 2.2
Name: jupyterlab_pachyderm
Version: 2.12.2
Summary: A JupyterLab extension.
Home-page: https://github.com/pachyderm/pachyderm
Author: 
Author-email: 
License: BSD-3-Clause
Keywords: jupyter,jupyterlab,jupyterlab-extension
Platform: Linux
Platform: Mac OS X
Platform: Windows
Classifier: License :: OSI Approved :: BSD License
Classifier: Programming Language :: Python
Classifier: Programming Language :: Python :: 3
Classifier: Programming Language :: Python :: 3.8
Classifier: Programming Language :: Python :: 3.9
Classifier: Programming Language :: Python :: 3.10
Classifier: Framework :: Jupyter
Classifier: Framework :: Jupyter :: JupyterLab
Classifier: Framework :: Jupyter :: JupyterLab :: 3
Classifier: Framework :: Jupyter :: JupyterLab :: Extensions
Classifier: Framework :: Jupyter :: JupyterLab :: Extensions :: Prebuilt
Requires-Python: <4,>=3.8
License-File: LICENSE
Requires-Dist: pyyaml<7.0,>=6.0
Requires-Dist: jupyter_server<2.15,>=2.14.1
Requires-Dist: pachyderm_sdk<2.11.0,>=2.10.1
Requires-Dist: certifi>=2024.7.4
Requires-Dist: idna!=3.6
Requires-Dist: jinja2!=3.1.3
Requires-Dist: tornado>=6.4.1
Requires-Dist: zipp>=3.19.1
Dynamic: home-page
Dynamic: keywords
Dynamic: license
Dynamic: requires-dist
Dynamic: summary
